LICENSE
MANIFEST.in
README.md
report.html
setup.py
htmlrunner/__init__.py
htmlrunner/exceptions.py
htmlrunner/loader.py
htmlrunner/result.py
htmlrunner/runner.py
htmlrunner.egg-info/PKG-INFO
htmlrunner.egg-info/SOURCES.txt
htmlrunner.egg-info/dependency_links.txt
htmlrunner.egg-info/requires.txt
htmlrunner.egg-info/top_level.txt
htmlrunner.egg-info/zip-safe
htmlrunner/templates/all.html
htmlrunner/templates/bootstrap_simple.html
htmlrunner/templates/green.html
htmlrunner/templates/htmltestreportcn.html
htmlrunner/templates/htmltestrunner_py3.html
htmlrunner/templates/pytest_html.html
htmlrunner/templates/pyunitreport.html
htmlrunner/templates/simple.html
htmlrunner/templates/simple2.html