Metadata-Version: 2.1
Name: htmlrunner
Version: 0.13
Summary: htmlrunner for unittest
Home-page: https://github.com/hanzhichao/htmlrunner
Author: Han Zhichao
Author-email: superhin@126.com
License: MIT license
Keywords: htmlrunner,testrunner,htmltestrunner
Platform: UNKNOWN
Classifier: Programming Language :: Python
Classifier: Programming Language :: Python :: 2.7
Classifier: Programming Language :: Python :: 3.7
